ipmap/__init__.py
ipmap/config.py
ipmap/data/settings.json
ipmap/data/templates/map.html
ipmap/ipmap.py
ipmap/main.py
ipmap/utils.py
ipmap-1.2.0.dist-info/LICENSE
ipmap-1.2.0.dist-info/METADATA
ipmap-1.2.0.dist-info/WHEEL
ipmap-1.2.0.dist-info/entry_points.txt
ipmap-1.2.0.dist-info/RECORD
