Metadata-Version: 2.1
Name: ipmap
Version: 1.2.0
Summary: A cross-platform easy-to-use ip geolocation & mapping tool.
Home-page: https://github.com/rly0nheart/ipmap
License: BSD-3-Clause
Keywords: mapping,geolocation,ip-address-geolocation,ip-address-lookup,ip-mapping
Author: Richard Mwewa
Author-email: rly0nheart@duck.com
Requires-Python: >=3.9,<4.0
Classifier: Development Status :: 5 - Production/Stable
Classifier: Intended Audience :: Information Technology
Classifier: License :: OSI Approved :: BSD License
Classifier: Natural Language :: English
Classifier: Operating System :: OS Independent
Classifier: Programming Language :: Python :: 3
Classifier: Programming Language :: Python :: 3.9
Classifier: Programming Language :: Python :: 3.10
Classifier: Programming Language :: Python :: 3.11
Requires-Dist: rich
Project-URL: Repository, https://github.com/rly0nheart/ipmap
